gdpshow.py
gdpshow-1.0.3.dist-info/METADATA
gdpshow-1.0.3.dist-info/WHEEL
gdpshow-1.0.3.dist-info/entry_points.txt
gdpshow-1.0.3.dist-info/top_level.txt
gdpshow-1.0.3.dist-info/RECORD
