Metadata-Version: 2.1
Name: gdpshow
Version: 1.0.3
Summary: A package for visualizing any countries GDP
Home-page: https://github.com/s2022001/
Author: Arima Naotaka
Author-email: s2022001@stu.musashino-u.ac.jp
License: UNKNOWN
Project-URL: Bug Tracker, https://github.com/s2022001/
Platform: UNKNOWN
Classifier: Programming Language :: Python :: 3
Requires-Python: >=3.7
Requires-Dist: pandas
Requires-Dist: matplotlib
